<?xml version="1.0" encoding="UTF-8"?>

<questions xmlns:xsi="http://www.w3.org/2001/XMLSchema-instance" xsi:noNamespaceSchemaLocation="quest.xsd">
	<question id="Q_01"> 
		<type>text</type>
		<title>Anomena el sòlid platònic que és el dual de l'icosaedre.</title>
		<answer>Dodecaedre</answer>
	</question>	

	<question id="Q_02"> 
		<type>text</type>
		<title>Anomena el sistema formal de geometria que no satisfà el cinquè postulat d'Euclides i te curvatura negativa</title>
		<answer>Geometria euclidiana</answer>
	</question>	

	<question id="Q_03"> 
		<type>select</type>
		<title>Indica quina identitat trigonomètrica és falsa:</title>
		<option>sin(-x) = sin(x + π)</option>
		<option>cos(x) = cos(x + π)</option>
		<option>tan(x) = cot(π/2 - x)</option>
		<option>cot(-x) = -cot(x)</option>
		<answer>2</answer>
	</question>
	
	<question id="Q_04"> 
		<type>select</type>
		<title>El producte infinit d'Euler equival a:</title>
		<option>2sin(2θ)</option>
		<option>cos(θ)/2</option>
		<option>sin(θ)/2</option>
		<option>sin(θ)/θ</option>
		<answer>4</answer>
	</question>

	<question id="Q_05"> 
		<type>checkbox</type>
		<title>Marca les afirmacions correctes referents a un cos algebraic (F,+,*)</title>
		<option>Existeix un element neutre per la suma i un altre element neutre per la multiplicació</option>
		<option>Tot element del cos té invers per la suma i la multiplicació</option>
		<option>Les operacions + i * són binàries en F</option>
		<option>(F,+,*) representa un anell commutatiu</option>
		<answer>1</answer>
		<answer>3</answer>
		<answer>4</answer>
	</question>

	<question id="Q_06"> 
		<type>checkbox</type>
		<title>Marca quins són exemples de cossos algebraics</title>
		<option>Els nombres naturals</option>
		<option>Els enters de Gauss</option>
		<option>Els nombres reals</option>
		<option>Un conjunt format només pels elements 0 i 1</option>
		<answer>3</answer>
		<answer>4</answer>
	</question>

	<question id="Q_07"> 
		<type>radio</type>
		<title>Donada una funció f integrable sobre l'interval [a,b], i definida F(x) sobre [a,b] per la seva integral d'extrems a i x de f(t)dt:</title>
		<option>Si f és contínua a un punt c de l'interval (a,b), aleshores F és derivable en c, i F'(c)=f(c)</option>
		<option>Si f és contínua a un punt c de l'interval (a,b), aleshores F és contínua en c, i F'(c)=f(c)</option>
		<option>Si f és contínua a un punt c de l'interval [a,b], aleshores F és derivable en c, i F'(c)=f(c)</option>
		<option>Cap de les respostes anteriors és correcta.</option>
		<answer>1</answer>
	</question>
	
	<question id="Q_08"> 
		<type>radio</type>
		<title>La integral de Lebesgue...</title>
		<option>data de principis del segle XVIII</option>
		<option>és l'única que defineix l'àrea avall d'una corba de convexitat positiva dins un entorn obert</option>
		<option>és l'extensió de la integral de Reimann a una classe ampliada de funcions reals que estén els possibles dominis en el qual les integrals es poden definir</option>
		<option>es difèrencia de la integral de Reimann en la que no manté la monotonia</option>
		<answer>3</answer>
	</question>

	<question id="Q_09"> 
		<type>multiple</type>
		<title>La transformada de Fourier:</title>
		<option>És empleada per transformar funcions entre el domini del temps i el domini de la freqüència</option>
		<option>Té la propietat de ser reversible</option>
		<option>Només és reversible si la funció és periòdica</option>
		<option>No es pot estendre a espais de funcions majors o a espais de funcions generalitzades</option>
		<answer>1</answer>
		<answer>2</answer>
	</question>	

	<question id="Q_10"> 
		<type>multiple</type>
		<title>Teorema fonamental de l'àlgebra:</title>
		<option>Tot polinomi de coeficients reals i de grau n major que zero, té exactament n arrels reals</option>
		<option>Tot polinomi de coeficients complexos i de grau n major que zero, té exactament n arrels</option>
		<option>El cos dels nombres complexos és obert per a les operacions algebraiques</option>
		<option>Tot polinomi en una variable de grau n major que zero amb coeficients reals o complexos té almenys una arrel real o complexa</option>
		<answer>2</answer>
		<answer>4</answer>
	</question>
</questions>
